bqtoolkit/__init__.py
bqtoolkit/_helpers.py
bqtoolkit/partition.py
bqtoolkit/table.py
bqtoolkit-0.0.3.dist-info/LICENSE.txt
bqtoolkit-0.0.3.dist-info/METADATA
bqtoolkit-0.0.3.dist-info/WHEEL
bqtoolkit-0.0.3.dist-info/top_level.txt
bqtoolkit-0.0.3.dist-info/RECORD
