Metadata-Version: 2.1
Name: bqtoolkit
Version: 0.0.3
Home-page: https://github.com/schmidtfederico/bqtoolkit
Author: Federico Schmidt
Author-email: schmidt.fdr@gmail.com
Classifier: Development Status :: 3 - Alpha
Classifier: Intended Audience :: Developers
Classifier: License :: OSI Approved :: MIT License
Classifier: Programming Language :: Python
Classifier: Programming Language :: Python :: 3
Classifier: Programming Language :: Python :: 3.6
Classifier: Programming Language :: Python :: 3.7
Classifier: Programming Language :: Python :: 3.8
Classifier: Programming Language :: Python :: 3.9
Classifier: Programming Language :: Python :: 3.10
Classifier: Operating System :: OS Independent
Classifier: Topic :: Internet
Requires-Python: >=3.6, <4
License-File: LICENSE.txt
Requires-Dist: google-cloud-bigquery (<3.0.0,>=1.24.0)
Requires-Dist: google-cloud-storage (<3.0.0,>=1.26.0)
Requires-Dist: importlib-metadata (<5.0)
